bypass_url_parser-0.4.4.dist-info/METADATA
bypass_url_parser-0.4.4.dist-info/WHEEL
bypass_url_parser-0.4.4.dist-info/entry_points.txt
bypass_url_parser-0.4.4.dist-info/licenses/LICENSE
bypass_url_parser/__init__.py
bypass_url_parser/_version.py
bypass_url_parser/payloads/header_http_methods.lst
bypass_url_parser/payloads/header_ip_hosts.lst
bypass_url_parser/payloads/header_ports.lst
bypass_url_parser/payloads/header_proto_schemes.lst
bypass_url_parser/payloads/header_urls.lst
bypass_url_parser/payloads/internal_endpaths.lst
bypass_url_parser/payloads/internal_http_methods.lst
bypass_url_parser/payloads/internal_ip_hosts.lst
bypass_url_parser/payloads/internal_midpaths.lst
bypass_url_parser/payloads/internal_ports.lst
bypass_url_parser/payloads/internal_proto_schemes.lst
bypass_url_parser/payloads/internal_user_agents.lst
bypass_url_parser-0.4.4.dist-info/RECORD
