Metadata-Version: 2.1
Name: bypass-url-parser
Version: 0.4.4
Summary: Default template for PDM package
Keywords: security
Author-Email: Laluka <loukajc@gmail.com>, jtof_fap <jtof_fap@insecurity.fr>, Gabriel Dugny <pypi@dugny.me>
License: AGPL-3.0-or-later
Classifier: Development Status :: 4 - Beta
Classifier: Intended Audience :: Information Technology
Classifier: License :: OSI Approved :: GNU Affero General Public License v3 or later (AGPLv3+)
Classifier: Programming Language :: Python :: 3
Classifier: Programming Language :: Python :: 3 :: Only
Classifier: Programming Language :: Python :: 3.8
Classifier: Programming Language :: Python :: 3.9
Classifier: Programming Language :: Python :: 3.10
Classifier: Programming Language :: Python :: 3.11
Classifier: Programming Language :: Python :: 3.12
Classifier: Programming Language :: Python :: 3.13
Classifier: Typing :: Typed
Classifier: Topic :: Security
Classifier: Operating System :: OS Independent
Classifier: Environment :: Console
Project-URL: Repository, https://github.com/laluka/bypass-url-parser
Project-URL: Changelog, https://github.com/laluka/bypass-url-parser/releases
Requires-Python: >=3.8
Requires-Dist: coloredlogs==15.0.1
Requires-Dist: docopt==0.6.2
